{
"skeleton": {
	"hash": "YCdWVirKNws",
	"spine": "4.1.19",
	"x": -274.73,
	"y": -17.71,
	"width": 565,
	"height": 1007.58,
	"images": "./images/",
	"audio": ""
},
"bones": [
	{ "name": "root" },
	{ "name": "trunk", "parent": "root", "length": 220.24, "rotation": 89.55, "x": 1.89, "y": 643.98 },
	{ "name": "dress", "parent": "trunk", "length": 532.99, "rotation": -179.55, "x": -4.78, "y": 1.27 },
	{ "name": "foot", "parent": "trunk", "length": 171.18, "rotation": 176.37, "x": -477.32, "y": -9.73 },
	{ "name": "head", "parent": "trunk", "length": 101.45, "x": 228.23, "y": 1.79 },
	{ "name": "left big arm", "parent": "trunk", "length": 134.55, "rotation": 169.73, "x": 159.57, "y": -93.51 },
	{ "name": "right big arm", "parent": "trunk", "length": 142.94, "rotation": 175.01, "x": 174.97, "y": 76.77 },
	{ "name": "left forearm", "parent": "left big arm", "length": 118.73, "rotation": -87.75, "x": 126.43, "y": -0.53 },
	{ "name": "right forearm", "parent": "right big arm", "length": 114.15, "rotation": -167.58, "x": 141.17, "y": 13.61 },
	{ "name": "left hand", "parent": "left forearm", "length": 84.85, "rotation": -10.78, "x": 120.3, "y": -10.42 },
	{ "name": "right hand", "parent": "right forearm", "length": 80, "rotation": 22.27, "x": 112.46, "y": 2.57 },
	{ "name": "2", "parent": "right hand", "length": 104.54, "rotation": -47.12, "x": 53.94, "y": -8.09 }
],
"slots": [
	{ "name": "Spot", "bone": "root" },
	{ "name": "foot", "bone": "foot", "attachment": "foot" },
	{ "name": "dress", "bone": "dress", "attachment": "dress" },
	{ "name": "trunk", "bone": "trunk", "attachment": "trunk" },
	{ "name": "left big arm", "bone": "left big arm", "attachment": "left big arm" },
	{ "name": "left forearm", "bone": "left forearm", "attachment": "left forearm" },
	{ "name": "right big arm", "bone": "right big arm", "attachment": "right big arm" },
	{ "name": "left hand", "bone": "left hand", "attachment": "left hand" },
	{ "name": "head", "bone": "head", "attachment": "head" },
	{ "name": "3", "bone": "2", "attachment": "3" },
	{ "name": "2", "bone": "2", "attachment": "2" },
	{ "name": "1", "bone": "2", "attachment": "1" },
	{ "name": "right hand", "bone": "right hand", "attachment": "right hand" },
	{ "name": "right forearm", "bone": "right forearm", "attachment": "right forearm" }
],
"skins": [
	{
		"name": "default",
		"attachments": {
			"1": {
				"1": { "x": 35.94, "y": 38.77, "rotation": -75.04, "width": 83, "height": 103 }
			},
			"2": {
				"2": { "x": -3.88, "y": -3.96, "rotation": -75.04, "width": 227, "height": 224 }
			},
			"3": {
				"3": { "x": -3.88, "y": -3.96, "rotation": -75.04, "width": 227, "height": 224 }
			},
			"dress": {
				"dress": {
					"type": "mesh",
					"uvs": [ 0.63847, 0.0329, 0.73695, 0.23721, 0.82856, 0.49725, 0.90643, 0.72427, 0.92704, 0.78206, 1, 0.85635, 0.81253, 0.92859, 0.54915, 0.95748, 0, 1, 0.03842, 0.84603, 0.09796, 0.73872, 0.13232, 0.61076, 0.25141, 0.26611, 0.36592, 0.03909, 0.42776, 0, 0.51479, 0, 0.57205, 0, 0.14377, 0.91207, 0.31554, 0.96161, 0.3728, 0.16911, 0.30409, 0.38374, 0.24683, 0.62934, 0.20332, 0.78825, 0.49647, 0.20626, 0.48502, 0.43327, 0.4896, 0.63346, 0.48273, 0.83365, 0.47813, 0.95873, 0.6316, 0.20832, 0.67282, 0.45185, 0.71634, 0.67887, 0.75756, 0.82333 ],
					"triangles": [ 19, 13, 14, 23, 14, 15, 19, 14, 23, 23, 15, 16, 16, 28, 23, 0, 28, 16, 28, 0, 1, 12, 13, 19, 20, 12, 19, 23, 20, 19, 24, 20, 23, 29, 28, 1, 29, 1, 2, 11, 12, 20, 21, 11, 20, 21, 20, 24, 24, 29, 25, 21, 24, 25, 28, 24, 23, 29, 24, 28, 30, 29, 2, 25, 29, 30, 30, 2, 3, 21, 10, 11, 22, 10, 21, 31, 30, 3, 31, 3, 4, 26, 21, 25, 26, 25, 30, 26, 30, 31, 22, 21, 26, 22, 9, 10, 17, 9, 22, 6, 31, 4, 6, 4, 5, 7, 26, 31, 7, 31, 6, 26, 18, 22, 27, 26, 7, 18, 17, 22, 26, 27, 18, 8, 9, 17, 8, 17, 18, 8, 18, 27, 8, 27, 7 ],
					"vertices": [ -13.43, 85.42, 114.68, 141.06, 277.72, 192.82, 420.06, 236.82, 456.29, 248.46, 502.88, 289.69, 548.17, 183.77, 566.28, 34.96, 592.94, -275.31, 496.41, -253.61, 429.12, -219.96, 348.89, -200.55, 132.79, -133.26, -9.55, -68.57, -34.06, -33.63, -34.06, 15.54, -34.06, 47.89, 537.81, -194.08, 568.87, -97.03, 71.97, -64.68, 206.55, -103.5, 360.54, -135.85, 460.17, -160.44, 95.27, 5.19, 237.61, -1.28, 363.12, 1.31, 488.64, -2.57, 567.07, -5.17, 96.56, 81.54, 249.25, 104.83, 391.59, 129.42, 482.17, 152.71 ],
					"hull": 17,
					"edges": [ 28, 26, 26, 24, 24, 22, 22, 20, 20, 18, 18, 34, 34, 36, 14, 12, 12, 10, 32, 0, 0, 2, 2, 4, 4, 6, 6, 8, 8, 10, 28, 38, 38, 40, 40, 42, 42, 44, 44, 34, 28, 30, 30, 32, 30, 46, 46, 48, 48, 50, 50, 52, 36, 54, 54, 14, 52, 54, 32, 56, 56, 58, 58, 60, 60, 62, 62, 12, 14, 16, 16, 18 ],
					"width": 565,
					"height": 627
				}
			},
			"foot": {
				"foot": {
					"x": 94.1,
					"y": 6.61,
					"scaleX": 0.8331,
					"scaleY": 0.8331,
					"rotation": 94.08,
					"width": 249,
					"height": 216
				}
			},
			"head": {
				"head": {
					"type": "mesh",
					"uvs": [ 0.78808, 0.26105, 0.87528, 0.52495, 0.78015, 0.85195, 0.54233, 1, 0.39171, 1, 0.19353, 0.87489, 0, 0.58805, 0.14597, 0.26679, 0.43135, 0.09468, 0.44721, 0.26105, 0.43928, 0.58805, 0.43135, 0.68558, 0.24902, 0.55937, 0.66917, 0.5651 ],
					"triangles": [ 9, 8, 0, 7, 8, 9, 12, 7, 9, 13, 9, 0, 13, 0, 1, 10, 12, 9, 13, 10, 9, 6, 7, 12, 11, 12, 10, 2, 13, 1, 5, 6, 12, 5, 12, 11, 4, 5, 11, 11, 13, 2, 13, 11, 10, 3, 11, 2, 4, 11, 3 ],
					"vertices": [ 92.66, -36.34, 52.62, -46.25, 2.84, -36.17, -19.87, -10.19, -20, 6.37, -1.16, 28.32, 42.27, 49.95, 91.23, 34.28, 117.64, 3.1, 92.36, 1.15, 42.65, 1.64, 27.82, 2.39, 46.85, 22.6, 46.34, -23.62 ],
					"hull": 9,
					"edges": [ 16, 14, 14, 12, 12, 10, 10, 8, 6, 8, 6, 4, 4, 2, 16, 0, 0, 2, 16, 18, 18, 20, 20, 22, 22, 6, 14, 24, 24, 10, 0, 26, 26, 4 ],
					"width": 110,
					"height": 152
				}
			},
			"left big arm": {
				"left big arm": { "x": 75.24, "y": -18.22, "rotation": 100.72, "width": 137, "height": 224 }
			},
			"left forearm": {
				"left forearm": { "x": 52.45, "y": -6.93, "rotation": -171.54, "width": 157, "height": 118 }
			},
			"left hand": {
				"left hand": { "x": 39.38, "y": -5.38, "rotation": -160.75, "width": 93, "height": 77 }
			},
			"right big arm": {
				"right big arm": { "x": 82.08, "y": 48.27, "rotation": 95.44, "width": 193, "height": 246 }
			},
			"right forearm": {
				"right forearm": { "x": 54.66, "y": 7.62, "rotation": -99.89, "width": 93, "height": 158 }
			},
			"right hand": {
				"right hand": {
					"type": "mesh",
					"uvs": [ 0.58604, 0.15845, 0.50242, 0.24456, 0.45838, 0.36871, 0.62546, 0.33025, 0.74756, 0.35264, 0.8901, 0.45953, 0.95441, 0.69177, 1, 0.8564, 1, 0.88784, 0.73208, 1, 0.66696, 1, 0.40866, 0.78775, 0.26202, 0.66726, 0.22801, 0.54382, 0.19037, 0.40717, 0.50348, 0.0909, 0.46934, 0.41732, 0.57387, 0.56325, 0.64794, 0.70485 ],
					"triangles": [ 1, 15, 0, 15, 1, 14, 1, 2, 14, 16, 2, 3, 14, 2, 16, 13, 14, 16, 17, 16, 3, 17, 3, 4, 17, 4, 5, 13, 16, 17, 12, 13, 17, 18, 17, 5, 6, 18, 5, 11, 12, 17, 18, 11, 17, 7, 18, 6, 7, 10, 18, 7, 9, 10, 11, 18, 10, 8, 9, 7 ],
					"vertices": [ 83.85, -32.39, 78.72, -20.17, 67.61, -8.45, 63.62, -23.91, 55.32, -31.81, 37.01, -35.62, 9.12, -25, -10.65, -17.47, -14, -15.36, -12.99, 12.8, -9.83, 17.82, 25.32, 23.48, 45.28, 26.7, 60.09, 21.04, 76.49, 14.77, 95.06, -30.56, 61.89, -6.04, 41.26, -4.3, 22.57, -0.51 ],
					"hull": 16,
					"edges": [ 14, 16, 16, 18, 18, 20, 28, 30, 2, 4, 8, 10, 0, 30, 2, 0, 4, 6, 6, 8, 6, 32, 24, 26, 26, 28, 32, 26, 10, 34, 34, 24, 10, 12, 12, 14, 12, 36, 20, 22, 22, 24, 36, 22 ],
					"width": 91,
					"height": 126
				}
			},
			"trunk": {
				"trunk": {
					"type": "mesh",
					"uvs": [ 0.46855, 0.29764, 0.64617, 0.31806, 0.66379, 0.347, 0.69057, 0.39099, 0.89039, 0.44641, 0.81491, 0.74394, 0.84155, 0.7877, 0.76162, 0.8052, 0.7705, 0.88396, 0.82379, 0.93938, 0.7261, 1, 0.33978, 1, 0.18436, 0.93355, 0.25985, 0.88104, 0.25985, 0.8227, 0.1888, 0.79937, 0.11332, 0.56601, 0.13108, 0.44349, 0.33534, 0.39391, 0.34048, 0.35172, 0.34422, 0.32098, 0.45523, 0.79645, 0.50408, 0.73811, 0.56624, 0.8052, 0.23654, 0.49216, 0.31163, 0.57985, 0.28243, 0.63192, 0.39715, 0.68124, 0.48475, 0.573, 0.59113, 0.69357, 0.71002, 0.62643, 0.66413, 0.57985, 0.7413, 0.49078, 0.35751, 0.43735, 0.48266, 0.41817, 0.6391, 0.43598, 0.43052, 0.38802, 0.53898, 0.39487, 0.62867, 0.36884 ],
					"triangles": [ 38, 0, 1, 38, 1, 2, 36, 20, 0, 37, 36, 0, 19, 20, 36, 38, 2, 3, 18, 19, 36, 38, 37, 0, 34, 36, 37, 35, 38, 3, 37, 38, 35, 34, 37, 35, 33, 18, 36, 33, 36, 34, 24, 17, 18, 32, 3, 4, 35, 3, 32, 33, 24, 18, 16, 17, 24, 28, 34, 35, 31, 28, 35, 33, 34, 28, 25, 24, 33, 32, 31, 35, 28, 25, 33, 16, 24, 25, 30, 31, 32, 26, 16, 25, 27, 25, 28, 26, 25, 27, 29, 28, 31, 29, 31, 30, 27, 28, 29, 22, 27, 29, 4, 30, 32, 5, 30, 4, 29, 30, 5, 21, 27, 22, 15, 16, 26, 15, 26, 27, 14, 15, 27, 23, 22, 29, 7, 23, 29, 21, 22, 23, 5, 7, 29, 7, 5, 6, 21, 14, 27, 13, 14, 21, 11, 13, 21, 12, 13, 11, 11, 21, 23, 8, 10, 23, 8, 23, 7, 10, 8, 9, 11, 23, 10 ],
					"vertices": [ 243.35, 3.8, 236.02, -40.13, 225.17, -44.57, 208.68, -51.31, 188.23, -100.83, 76.22, -83.06, 59.82, -89.77, 53.08, -70.08, 23.49, -72.51, 2.75, -85.84, -20.23, -61.89, -20.98, 33.53, 3.7, 72.11, 23.59, 53.62, 45.53, 53.8, 54.16, 71.41, 141.76, 90.75, 187.85, 86.72, 206.9, 36.42, 222.77, 35.28, 234.33, 34.44, 55.78, 5.62, 77.81, -6.27, 52.7, -21.83, 169.76, 60.53, 136.94, 41.73, 117.3, 48.78, 98.98, 20.3, 139.85, -1.01, 94.72, -27.64, 120.2, -56.81, 137.62, -45.34, 171.26, -64.14, 190.6, 30.81, 198.06, -0.04, 191.67, -38.73, 209.29, 12.93, 206.93, -13.88, 216.89, -35.96 ],
					"hull": 21,
					"edges": [ 36, 34, 34, 32, 32, 30, 30, 28, 28, 26, 26, 24, 24, 22, 20, 22, 20, 18, 18, 16, 16, 14, 14, 12, 12, 10, 10, 8, 8, 6, 2, 0, 0, 40, 28, 42, 42, 44, 44, 46, 46, 14, 48, 50, 50, 52, 52, 54, 54, 56, 56, 58, 58, 60, 60, 62, 62, 64, 48, 66, 66, 68, 68, 70, 70, 64, 36, 38, 38, 40, 38, 72, 72, 74, 74, 76, 2, 4, 4, 6, 76, 4 ],
					"width": 247,
					"height": 376
				}
			}
		}
	}
],
"animations": {
	"animation": {
		"slots": {
			"2": {
				"rgba": [
					{ "color": "ffffff00", "curve": "stepped" },
					{
						"time": 0.7667,
						"color": "ffffff00",
						"curve": [ 0.778, 1, 0.789, 1, 0.778, 1, 0.789, 1, 0.778, 1, 0.789, 1, 0.778, 0, 0.789, 1 ]
					},
					{ "time": 0.8, "color": "ffffffff", "curve": "stepped" },
					{ "time": 2.2, "color": "ffffffff", "curve": "stepped" },
					{
						"time": 2.2667,
						"color": "ffffffff",
						"curve": [ 2.278, 1, 2.289, 1, 2.278, 1, 2.289, 1, 2.278, 1, 2.289, 1, 2.278, 1, 2.289, 0 ]
					},
					{ "time": 2.3, "color": "ffffff00", "curve": "stepped" },
					{ "time": 2.6667, "color": "ffffff00" }
				]
			},
			"3": {
				"rgba": [
					{ "color": "ffffff00", "curve": "stepped" },
					{
						"time": 0.8,
						"color": "ffffff00",
						"curve": [ 0.811, 1, 0.822, 1, 0.811, 1, 0.822, 1, 0.811, 1, 0.822, 1, 0.811, 0, 0.822, 1 ]
					},
					{ "time": 0.8333, "color": "ffffffff", "curve": "stepped" },
					{ "time": 2.2, "color": "ffffffff", "curve": "stepped" },
					{
						"time": 2.2333,
						"color": "ffffffff",
						"curve": [ 2.244, 1, 2.256, 1, 2.244, 1, 2.256, 1, 2.244, 1, 2.256, 1, 2.244, 1, 2.256, 0 ]
					},
					{ "time": 2.2667, "color": "ffffff00", "curve": "stepped" },
					{ "time": 2.6667, "color": "ffffff00" }
				]
			}
		},
		"bones": {
			"trunk": {
				"rotate": [
					{ "curve": "stepped" },
					{ "time": 2.6667 }
				],
				"translate": [
					{
						"curve": [ 0.444, 0, 0.889, -1.7, 0.444, 0, 0.889, -17.01 ]
					},
					{
						"time": 1.3333,
						"x": -1.7,
						"y": -17.01,
						"curve": [ 1.778, -1.7, 2.222, 0, 1.778, -17.01, 2.222, 0 ]
					},
					{ "time": 2.6667 }
				]
			},
			"foot": {
				"rotate": [
					{ "curve": "stepped" },
					{ "time": 2.6667 }
				],
				"translate": [
					{
						"curve": [ 0.444, 0, 0.889, 20.45, 0.444, 0, 0.889, -4.94 ]
					},
					{
						"time": 1.3333,
						"x": 20.45,
						"y": -4.94,
						"curve": [ 1.778, 20.45, 2.222, 0, 1.778, -4.94, 2.222, 0 ]
					},
					{ "time": 2.6667 }
				]
			},
			"head": {
				"rotate": [
					{
						"curve": [ 0.5, 0, 1, 7.32 ]
					},
					{
						"time": 1.5,
						"value": 7.32,
						"curve": [ 1.889, 7.32, 2.278, 0 ]
					},
					{ "time": 2.6667 }
				],
				"translate": [
					{
						"x": -1.12,
						"y": -6.21,
						"curve": [ 0.5, -1.12, 1, -12.67, 0.5, -6.21, 1, -2.59 ]
					},
					{
						"time": 1.5,
						"x": -12.67,
						"y": -2.59,
						"curve": [ 1.889, -12.67, 2.278, -1.12, 1.889, -2.59, 2.278, -6.21 ]
					},
					{ "time": 2.6667, "x": -1.12, "y": -6.21 }
				]
			},
			"right forearm": {
				"rotate": [
					{
						"curve": [ 0.222, 0, 0.444, 15.53 ]
					},
					{
						"time": 0.6667,
						"value": 15.53,
						"curve": [ 0.722, 15.53, 0.778, -37.62 ]
					},
					{
						"time": 0.8333,
						"value": -39.48,
						"curve": [ 0.922, -42.45, 1.011, -42.45 ]
					},
					{
						"time": 1.1,
						"value": -42.45,
						"curve": [ 1.256, -42.45, 1.411, -39.06 ]
					},
					{
						"time": 1.5667,
						"value": -39.06,
						"curve": [ 1.767, -39.06, 1.967, -42.68 ]
					},
					{
						"time": 2.1667,
						"value": -42.68,
						"curve": [ 2.222, -42.68, 2.278, 3.83 ]
					},
					{
						"time": 2.3333,
						"value": 3.83,
						"curve": [ 2.444, 3.83, 2.556, 0 ]
					},
					{ "time": 2.6667 }
				],
				"translate": [
					{ "curve": "stepped" },
					{ "time": 2.6667 }
				]
			},
			"2": {
				"rotate": [
					{
						"curve": [ 0.222, 0, 0.444, 10.54 ]
					},
					{
						"time": 0.6667,
						"value": 10.54,
						"curve": [ 0.889, 10.54, 1.111, -10.48 ]
					},
					{
						"time": 1.3333,
						"value": -10.48,
						"curve": [ 1.722, -10.48, 2.111, 14.43 ]
					},
					{
						"time": 2.5,
						"value": 14.43,
						"curve": [ 2.556, 14.43, 2.611, 0 ]
					},
					{ "time": 2.6667 }
				]
			},
			"right hand": {
				"rotate": [
					{
						"curve": [ 0.233, 0, 0.467, 13.05 ]
					},
					{
						"time": 0.7,
						"value": 13.05,
						"curve": [ 0.789, 13.05, 0.878, -19.42 ]
					},
					{
						"time": 0.9667,
						"value": -19.42,
						"curve": [ 1.244, -19.42, 1.522, -3.16 ]
					},
					{
						"time": 1.8,
						"value": -3.16,
						"curve": [ 1.911, -3.16, 2.022, -12 ]
					},
					{
						"time": 2.1333,
						"value": -12,
						"curve": [ 2.311, -12, 2.489, 0 ]
					},
					{ "time": 2.6667 }
				],
				"translate": [
					{ "curve": "stepped" },
					{ "time": 2.6667 }
				]
			},
			"left big arm": {
				"rotate": [
					{
						"curve": [ 0.422, 0, 0.844, 3.93 ]
					},
					{
						"time": 1.2667,
						"value": 3.93,
						"curve": [ 1.733, 3.93, 2.2, 0 ]
					},
					{ "time": 2.6667 }
				],
				"translate": [
					{
						"curve": [ 0.422, 0, 0.844, -1.24, 0.422, 0, 0.844, -0.01 ]
					},
					{
						"time": 1.2667,
						"x": -1.24,
						"y": -0.01,
						"curve": [ 1.733, -1.24, 2.2, 0, 1.733, -0.01, 2.2, 0 ]
					},
					{ "time": 2.6667 }
				]
			},
			"left forearm": {
				"rotate": [
					{
						"curve": [ 0.422, 0, 0.844, -8.98 ]
					},
					{
						"time": 1.2667,
						"value": -8.98,
						"curve": [ 1.733, -8.98, 2.2, 0 ]
					},
					{ "time": 2.6667 }
				],
				"translate": [
					{ "curve": "stepped" },
					{ "time": 2.6667 }
				]
			},
			"left hand": {
				"rotate": [
					{
						"curve": [ 0.444, 0, 0.889, 23.68 ]
					},
					{
						"time": 1.3333,
						"value": 23.68,
						"curve": [ 1.778, 23.68, 2.222, 0 ]
					},
					{ "time": 2.6667 }
				],
				"translate": [
					{ "curve": "stepped" },
					{ "time": 2.6667 }
				]
			},
			"right big arm": {
				"rotate": [
					{
						"curve": [ 0.433, 0, 0.867, 2.94 ]
					},
					{
						"time": 1.3,
						"value": 2.94,
						"curve": [ 1.756, 2.94, 2.211, 0 ]
					},
					{ "time": 2.6667 }
				],
				"translate": [
					{
						"curve": [ 0.433, 0, 0.867, -9.23, 0.433, 0, 0.867, 0 ]
					},
					{
						"time": 1.3,
						"x": -9.23,
						"curve": [ 1.756, -9.23, 2.211, 0, 1.756, 0, 2.211, 0 ]
					},
					{ "time": 2.6667 }
				]
			}
		},
		"attachments": {
			"default": {
				"dress": {
					"dress": {
						"deform": [
							{
								"curve": [ 0.444, 0, 0.889, 1 ]
							},
							{
								"time": 1.3333,
								"vertices": [ 1.42603, -2.85196, 3.32605, -4.98898, 1.66302, -9.97797, 6.17792, -14.25601, 6.17792, -14.25601, 5.46698, 11.64096, -4.63196, 25.84, 5.94092, 17.34894, 1.66296, -1.66303, 10.45599, -8.31494, 7.604, 13.7821, 9.26691, 13.78198, 4.98895, 11.64105, 0, 5.70397, 0, 0, 0, 0, 0, 0, 23.28595, 16.63388, 7.13, 0, 2.85199, 9.98199, 2.85199, 9.98199, 2.85199, 9.98199, 2.85199, 9.98199, 1.42596, 19.78201, 1.42596, 19.78201, 1.42596, 19.78201, -2.31604, 27.26602, 4.81396, 27.26602, -4.27795, 7.12994, -4.27795, 14.61395, -6.14899, 20.22693, -6.14899, 20.22693 ],
								"curve": [ 1.778, 0, 2.222, 1 ]
							},
							{ "time": 2.6667 }
						]
					}
				},
				"head": {
					"head": {
						"deform": [
							{
								"curve": [ 0.5, 0, 1, 1 ]
							},
							{
								"time": 1.5,
								"vertices": [ -0.17523, -1.44469, 5.01233, -1.0098, 3.07166, -1.00977, -3.78668, -1.0098, -3.78668, -1.0098, 3.07166, -1.00977, 3.30615, -3.00301, -0.17523, -1.44469, -0.17523, -1.44469, -16.01312, -1.2102, -6.6767, -0.66176, -16.50372, -0.86214, -12.80371, -0.57475, -12.0813, -0.66174 ],
								"curve": [ 1.889, 0, 2.278, 1 ]
							},
							{ "time": 2.6667 }
						]
					}
				},
				"right hand": {
					"right hand": {
						"deform": [
							{
								"vertices": [ 9.922, 2.75232, 6.93298, 1.00543, 4.27637, -2.27246, 0, 0, 0, 0, 0, 0, 0, 0, 0, 0, 0, 0, 0, 0, 0, 0, 0, 0, 0, 0, 0, 0, -2.04297, -0.76492, 9.06616, 5.59171 ],
								"curve": [ 0.156, 0, 0.311, 1 ]
							},
							{
								"time": 0.4667,
								"vertices": [ 16.33112, 8.43726, 11.40204, 4.84247, 7.3288, -1.37701, 0, 0, 0, 0, 0, 0, 0, 0, 0, 0, 0, 0, 0, 0, 0, 0, 0, 0, 0, 0, 0, 0, -4.01807, 0.13992, 14.32446, 13.26279 ],
								"curve": [ 0.711, 0, 0.956, 1 ]
							},
							{
								"time": 1.2,
								"vertices": [ -6.22272, -3.42825, -1.17493, -2.39352, 1.04993, -1.24026, 0, 0, 0, 0, 0, 0, 0, 0, 0, 0, 0, 0, 0, 0, 0, 0, 0, 0, 0, 0, 0, 0, 11.58722, -7.36386, -7.30804, -11.01883 ],
								"curve": "stepped"
							},
							{
								"time": 1.9,
								"vertices": [ -6.22272, -3.42825, -1.17493, -2.39352, 1.04993, -1.24026, 0, 0, 0, 0, 0, 0, 0, 0, 0, 0, 0, 0, 0, 0, 0, 0, 0, 0, 0, 0, 0, 0, 11.58722, -7.36386, -7.30804, -11.01883 ],
								"curve": [ 2.156, 0, 2.411, 1 ]
							},
							{
								"time": 2.6667,
								"vertices": [ 9.922, 2.75232, 6.93298, 1.00543, 4.27637, -2.27246, 0, 0, 0, 0, 0, 0, 0, 0, 0, 0, 0, 0, 0, 0, 0, 0, 0, 0, 0, 0, 0, 0, -2.04297, -0.76492, 9.06616, 5.59171 ]
							}
						]
					}
				},
				"trunk": {
					"trunk": {
						"deform": [
							{
								"curve": [ 0.444, 0, 0.889, 1 ]
							},
							{
								"time": 1.3333,
								"offset": 4,
								"vertices": [ -6.76678, -1.0E-5, -3.83429, 0, -8.41345, -1.0E-5, 0, 0, 0, 0, 0, 0, 0, 0, 0, 0, 0, 0, 0, 0, 0, 0, 0, 0, 0, 0, 0, 0, 0, 0, -8.41345, -1.0E-5, -3.83429, 0, -6.76678, -1.0E-5, 0, 0, 0, 0, 0, 0, 0, 0, -7.71539, 0, -2.57587, 0, -2.57587, 0, -2.57587, 0, -2.57587, 0, -2.57587, 0, -2.57587, 0, -2.57587, 0, -5.66699, 0, -7.71539, 0, -2.57587, 0, -5.66699, 0, -11.29578, -1.0E-5, -11.29578, -1.0E-5, -11.29578 ],
								"curve": [ 1.778, 0, 2.222, 1 ]
							},
							{ "time": 2.6667 }
						]
					}
				}
			}
		}
	},
	"breath": {
		"slots": {
			"2": {
				"rgba": [
					{ "color": "ffffff00", "curve": "stepped" },
					{ "time": 2.6667, "color": "ffffff00" }
				]
			},
			"3": {
				"rgba": [
					{ "color": "ffffff00", "curve": "stepped" },
					{ "time": 2.6667, "color": "ffffff00" }
				]
			}
		},
		"bones": {
			"trunk": {
				"rotate": [
					{ "curve": "stepped" },
					{ "time": 2.6667 }
				],
				"translate": [
					{
						"curve": [ 0.333, 0, 1, -1.7, 0.333, 0, 1, -17.01 ]
					},
					{
						"time": 1.3333,
						"x": -1.7,
						"y": -17.01,
						"curve": [ 1.667, -1.7, 2.333, 0, 1.667, -17.01, 2.333, 0 ]
					},
					{ "time": 2.6667 }
				]
			},
			"head": {
				"rotate": [
					{
						"curve": [ 0.375, 0, 1.125, 7.32 ]
					},
					{
						"time": 1.5,
						"value": 7.32,
						"curve": [ 1.792, 7.32, 2.375, 0 ]
					},
					{ "time": 2.6667 }
				],
				"translate": [
					{
						"curve": [ 0.375, 0, 1.125, 3.06, 0.375, 0, 1.125, -0.5 ]
					},
					{
						"time": 1.5,
						"x": 3.06,
						"y": -0.5,
						"curve": [ 1.792, 3.06, 2.375, 0, 1.792, -0.5, 2.375, 0 ]
					},
					{ "time": 2.6667 }
				]
			},
			"left hand": {
				"rotate": [
					{
						"curve": [ 0.333, 0, 1, 14.54 ]
					},
					{
						"time": 1.3333,
						"value": 14.54,
						"curve": [ 1.667, 14.54, 2.333, 0 ]
					},
					{ "time": 2.6667 }
				],
				"translate": [
					{ "curve": "stepped" },
					{ "time": 2.6667 }
				]
			},
			"left forearm": {
				"rotate": [
					{
						"curve": [ 0.317, 0, 0.95, -8.98 ]
					},
					{
						"time": 1.2667,
						"value": -8.98,
						"curve": [ 1.617, -8.98, 2.317, 0 ]
					},
					{ "time": 2.6667 }
				],
				"translate": [
					{ "curve": "stepped" },
					{ "time": 2.6667 }
				]
			},
			"right forearm": {
				"rotate": [
					{
						"curve": [ 0.311, 0, 0.767, 3.09 ]
					},
					{
						"time": 1.2333,
						"value": 6.41,
						"curve": [ 1.765, 3.33, 2.311, 0 ]
					},
					{ "time": 2.6667 }
				],
				"translate": [
					{ "curve": "stepped" },
					{ "time": 2.6667 }
				]
			},
			"foot": {
				"rotate": [
					{ "curve": "stepped" },
					{ "time": 2.6667 }
				],
				"translate": [
					{
						"curve": [ 0.333, 0, 1, 20.45, 0.333, 0, 1, -4.94 ]
					},
					{
						"time": 1.3333,
						"x": 20.45,
						"y": -4.94,
						"curve": [ 1.667, 20.45, 2.333, 0, 1.667, -4.94, 2.333, 0 ]
					},
					{ "time": 2.6667 }
				]
			},
			"right hand": {
				"rotate": [
					{
						"curve": [ 0.333, 0, 0.833, 3.91 ]
					},
					{
						"time": 1.3333,
						"value": 7.81,
						"curve": [ 1.833, 3.91, 2.333, 0 ]
					},
					{ "time": 2.6667 }
				],
				"translate": [
					{ "curve": "stepped" },
					{ "time": 2.6667 }
				]
			},
			"right big arm": {
				"rotate": [
					{
						"curve": [ 0.325, 0, 0.975, 2.94 ]
					},
					{
						"time": 1.3,
						"value": 2.94,
						"curve": [ 1.642, 2.94, 2.325, 0 ]
					},
					{ "time": 2.6667 }
				],
				"translate": [
					{ "curve": "stepped" },
					{ "time": 2.6667 }
				]
			},
			"left big arm": {
				"rotate": [
					{
						"curve": [ 0.317, 0, 0.95, 3.93 ]
					},
					{
						"time": 1.2667,
						"value": 3.93,
						"curve": [ 1.617, 3.93, 2.317, 0 ]
					},
					{ "time": 2.6667 }
				],
				"translate": [
					{
						"curve": [ 0.317, 0, 0.95, -1.24, 0.317, 0, 0.95, -0.01 ]
					},
					{
						"time": 1.2667,
						"x": -1.24,
						"y": -0.01,
						"curve": [ 1.617, -1.24, 2.317, 0, 1.617, -0.01, 2.317, 0 ]
					},
					{ "time": 2.6667 }
				]
			}
		},
		"attachments": {
			"default": {
				"dress": {
					"dress": {
						"deform": [
							{
								"curve": [ 0.333, 0, 1, 1 ]
							},
							{
								"time": 1.3333,
								"vertices": [ 1.42603, -2.85196, 3.32605, -4.98898, 1.66302, -9.97797, 6.17792, -14.25601, 6.17792, -14.25601, 5.46698, 11.64096, -4.63196, 25.84, 5.94092, 17.34894, 1.66296, -1.66303, 10.45599, -8.31494, 7.604, 13.7821, 9.26691, 13.78198, 4.98895, 11.64105, 0, 5.70397, 0, 0, 0, 0, 0, 0, 23.28595, 16.63388, 7.13, 0, 2.85199, 9.98199, 2.85199, 9.98199, 2.85199, 9.98199, 2.85199, 9.98199, 1.42596, 19.78201, 1.42596, 19.78201, 1.42596, 19.78201, -2.31604, 27.26602, 4.81396, 27.26602, -4.27795, 7.12994, -4.27795, 14.61395, -6.14899, 20.22693, -6.14899, 20.22693 ],
								"curve": [ 1.667, 0, 2.333, 1 ]
							},
							{ "time": 2.6667 }
						]
					}
				},
				"head": {
					"head": {
						"deform": [
							{
								"curve": [ 0.375, 0, 1.125, 1 ]
							},
							{
								"time": 1.5,
								"vertices": [ -0.17523, -1.44469, -3.78668, -1.0098, -3.78668, -1.0098, -3.78668, -1.0098, -3.78668, -1.0098, -3.78668, -1.0098, -5.49286, -3.00301, -0.17523, -1.44469, -0.17523, -1.44469, -8.20874, -1.21021, -6.6767, -0.66176, -11.09912, -0.86217, -7.39911, -0.57477, -6.6767, -0.66176 ],
								"curve": [ 1.792, 0, 2.375, 1 ]
							},
							{ "time": 2.6667 }
						]
					}
				}
			}
		}
	},
	"hologram": {
		"slots": {
			"1": {
				"rgba": [
					{ "color": "ffffffff" },
					{ "time": 0.6667, "color": "b0b1ffeb" },
					{ "time": 1.3333, "color": "ffb0fd8c" },
					{ "time": 2.1667, "color": "65ff9e92" }
				]
			},
			"2": {
				"rgba": [
					{
						"color": "ecf0ff00",
						"curve": [ 0.163, 0.93, 0.467, 0.74, 0.163, 0.94, 0.467, 0.75, 0.163, 1, 0.467, 1, 0.163, 0, 0.467, 0 ]
					},
					{
						"time": 0.6667,
						"color": "b0b1ff00",
						"curve": [ 0.703, 0.89, 0.737, 1, 0.703, 0.89, 0.737, 1, 0.703, 1, 0.737, 1, 0.703, 0, 0.737, 0 ]
					},
					{
						"time": 0.7667,
						"color": "ffffff00",
						"curve": [ 0.775, 1, 0.792, 1, 0.775, 1, 0.792, 1, 0.775, 1, 0.792, 1, 0.775, 0, 0.792, 1 ]
					},
					{
						"time": 0.8,
						"color": "ffffffff",
						"curve": [ 0.938, 1, 1.13, 1, 0.938, 1, 1.13, 0.86, 0.938, 1, 1.13, 1, 0.938, 1, 1.13, 0.8 ]
					},
					{
						"time": 1.3333,
						"color": "ffb0fd8c",
						"curve": [ 1.63, 0.75, 1.956, 0.42, 1.63, 0.82, 1.956, 0.99, 1.63, 0.84, 1.956, 0.63, 1.63, 0.56, 1.956, 0.57 ]
					},
					{
						"time": 2.1667,
						"color": "65ff9e92",
						"curve": [ 2.178, 0.8, 2.189, 1, 2.178, 1, 2.189, 1, 2.178, 0.87, 2.189, 1, 2.178, 0.86, 2.189, 1 ]
					},
					{ "time": 2.2, "color": "ffffffff", "curve": "stepped" },
					{
						"time": 2.2667,
						"color": "ffffffff",
						"curve": [ 2.275, 1, 2.292, 1, 2.275, 1, 2.292, 1, 2.275, 1, 2.292, 1, 2.275, 1, 2.292, 0 ]
					},
					{ "time": 2.3, "color": "ffffff00", "curve": "stepped" },
					{ "time": 2.6667, "color": "ffffff00" }
				]
			},
			"3": {
				"rgba": [
					{
						"color": "ffffff00",
						"curve": [ 0.162, 1, 0.459, 0.77, 0.162, 1, 0.459, 0.77, 0.162, 1, 0.459, 1, 0.162, 0, 0.459, 0 ]
					},
					{
						"time": 0.6667,
						"color": "b0b1ff00",
						"curve": [ 0.716, 0.88, 0.761, 1, 0.716, 0.89, 0.761, 1, 0.716, 1, 0.761, 1, 0.716, 0, 0.761, 0 ]
					},
					{
						"time": 0.8,
						"color": "ffffff00",
						"curve": [ 0.808, 1, 0.825, 1, 0.808, 1, 0.825, 1, 0.808, 1, 0.825, 1, 0.808, 0, 0.825, 1 ]
					},
					{
						"time": 0.8333,
						"color": "ffffffff",
						"curve": [ 0.964, 1, 1.142, 1, 0.964, 1, 1.142, 0.86, 0.964, 1, 1.142, 1, 0.964, 1, 1.142, 0.8 ]
					},
					{
						"time": 1.3333,
						"color": "ffb0fd8c",
						"curve": [ 1.628, 0.75, 1.956, 0.42, 1.628, 0.82, 1.956, 0.99, 1.628, 0.84, 1.956, 0.64, 1.628, 0.56, 1.956, 0.57 ]
					},
					{
						"time": 2.1667,
						"color": "65ff9e92",
						"curve": [ 2.178, 0.8, 2.189, 1, 2.178, 1, 2.189, 1, 2.178, 0.87, 2.189, 1, 2.178, 0.86, 2.189, 1 ]
					},
					{ "time": 2.2, "color": "ffffffff", "curve": "stepped" },
					{
						"time": 2.2333,
						"color": "ffffffff",
						"curve": [ 2.242, 1, 2.258, 1, 2.242, 1, 2.258, 1, 2.242, 1, 2.258, 1, 2.242, 1, 2.258, 0 ]
					},
					{ "time": 2.2667, "color": "ffffff00", "curve": "stepped" },
					{ "time": 2.6667, "color": "ffffff00" }
				]
			},
			"dress": {
				"rgba": [
					{ "color": "ffffffff" },
					{ "time": 0.3333, "color": "ffffff71" },
					{ "time": 0.5333, "color": "ffffffff" },
					{ "time": 0.6667, "color": "b0b1ffeb" },
					{ "time": 1.3333, "color": "ffb0fd8c" },
					{ "time": 1.9, "color": "ffffffff" },
					{ "time": 2.1667, "color": "65ff9e92" },
					{ "time": 2.3333, "color": "ffffff4e" },
					{ "time": 2.6667, "color": "ffffffff" }
				]
			},
			"foot": {
				"rgba": [
					{ "color": "ffffffff" },
					{ "time": 0.3333, "color": "ffffff71" },
					{ "time": 0.5333, "color": "ffffffff" },
					{ "time": 0.6667, "color": "b0b1ffeb" },
					{ "time": 1.3333, "color": "ffb0fd8c" },
					{ "time": 1.9, "color": "ffffffff" },
					{ "time": 2.1667, "color": "65ff9e92" },
					{ "time": 2.3333, "color": "ffffff4e" }
				]
			},
			"head": {
				"rgba": [
					{ "color": "ffffffff" },
					{ "time": 0.3333, "color": "ffffff71" },
					{ "time": 0.5333, "color": "ffffffff" },
					{ "time": 0.6667, "color": "b0b1ffeb" },
					{ "time": 1.3333, "color": "ffb0fd8c" },
					{ "time": 1.9, "color": "ffffffff" },
					{ "time": 2.1667, "color": "65ff9e92" },
					{ "time": 2.3333, "color": "ffffff4e" }
				]
			},
			"left big arm": {
				"rgba": [
					{ "color": "ffffffff" },
					{ "time": 0.3333, "color": "ffffff71" },
					{ "time": 0.5333, "color": "ffffffff" },
					{ "time": 0.6667, "color": "b0b1ffeb" },
					{ "time": 1.3333, "color": "ffb0fd8c" },
					{ "time": 1.9, "color": "ffffffff" },
					{ "time": 2.1667, "color": "65ff9e92" },
					{ "time": 2.3333, "color": "ffffff4e" },
					{ "time": 2.6667, "color": "ffffffff" }
				]
			},
			"left forearm": {
				"rgba": [
					{ "color": "ffffffff" },
					{ "time": 0.3333, "color": "ffffff71" },
					{ "time": 0.5333, "color": "ffffffff" },
					{ "time": 0.6667, "color": "b0b1ffeb" },
					{ "time": 1.3333, "color": "ffb0fd8c" },
					{ "time": 1.9, "color": "ffffffff" },
					{ "time": 2.1667, "color": "65ff9e92" },
					{ "time": 2.3333, "color": "ffffff4e" },
					{ "time": 2.6667, "color": "ffffffff" }
				]
			},
			"left hand": {
				"rgba": [
					{ "color": "ffffffff" },
					{ "time": 0.3333, "color": "ffffff71" },
					{ "time": 0.5333, "color": "ffffffff" },
					{ "time": 0.6667, "color": "b0b1ffeb" },
					{ "time": 1.3333, "color": "ffb0fd8c" },
					{ "time": 1.9, "color": "ffffffff" },
					{ "time": 2.1667, "color": "65ff9e92" },
					{ "time": 2.3333, "color": "ffffff4e" }
				]
			},
			"right big arm": {
				"rgba": [
					{ "color": "ffffffff" },
					{ "time": 0.3333, "color": "ffffff71" },
					{ "time": 0.5333, "color": "ffffffff" },
					{ "time": 0.6667, "color": "b0b1ffeb" },
					{ "time": 1.3333, "color": "ffb0fd8c" },
					{ "time": 1.9, "color": "ffffffff" },
					{ "time": 2.1667, "color": "65ff9e92" },
					{ "time": 2.3333, "color": "ffffff4e" },
					{ "time": 2.6667, "color": "ffffffff" }
				]
			},
			"right forearm": {
				"rgba": [
					{ "color": "ffffffff" },
					{ "time": 0.3333, "color": "ffffff71" },
					{ "time": 0.5333, "color": "ffffffff" },
					{ "time": 0.6667, "color": "b0b1ffeb" },
					{ "time": 1.3333, "color": "ffb0fd8c" },
					{ "time": 1.9, "color": "ffffffff" },
					{ "time": 2.1667, "color": "65ff9e92" },
					{ "time": 2.3333, "color": "ffffff4e" },
					{ "time": 2.6667, "color": "ffffffff" }
				]
			},
			"right hand": {
				"rgba": [
					{ "color": "ffffffff" },
					{ "time": 0.3333, "color": "ffffff71" },
					{ "time": 0.5333, "color": "ffffffff" },
					{ "time": 0.6667, "color": "b0b1ffeb" },
					{ "time": 1.3333, "color": "ffb0fd8c" },
					{ "time": 1.9, "color": "ffffffff" },
					{ "time": 2.1667, "color": "65ff9e92" },
					{ "time": 2.3333, "color": "ffffff4e" },
					{ "time": 2.6667, "color": "ffffffff" }
				]
			},
			"Spot": {
				"rgba": [
					{ "color": "ffffffff" },
					{ "time": 0.3333, "color": "ffffff71" },
					{ "time": 0.5333, "color": "ffffffff" },
					{ "time": 0.6667, "color": "b0b1ffeb" },
					{ "time": 1.3333, "color": "ffb0fd8c" },
					{ "time": 1.9, "color": "ffffffff" },
					{ "time": 2.1667, "color": "65ff9e92" },
					{ "time": 2.3333, "color": "ffffff4e" },
					{ "time": 2.6667, "color": "ffffffff" }
				]
			},
			"trunk": {
				"rgba": [
					{ "color": "ffffffff" },
					{ "time": 0.3333, "color": "ffffff71" },
					{ "time": 0.5333, "color": "ffffffff" },
					{ "time": 0.6667, "color": "b0b1ffeb" },
					{ "time": 1.3333, "color": "ffb0fd8c" },
					{ "time": 1.9, "color": "ffffffff" },
					{ "time": 2.1667, "color": "65ff9e92" },
					{ "time": 2.3333, "color": "ffffff4e" },
					{ "time": 2.6667, "color": "ffffffff" }
				]
			}
		},
		"bones": {
			"left big arm": {
				"rotate": [
					{
						"curve": [ 0.317, 0, 0.95, 3.93 ]
					},
					{
						"time": 1.2667,
						"value": 3.93,
						"curve": [ 1.617, 3.93, 2.317, 0 ]
					},
					{ "time": 2.6667 }
				],
				"translate": [
					{
						"curve": [ 0.317, 0, 0.95, -1.24, 0.317, 0, 0.95, -0.01 ]
					},
					{
						"time": 1.2667,
						"x": -1.24,
						"y": -0.01,
						"curve": [ 1.617, -1.24, 2.317, 0, 1.617, -0.01, 2.317, 0 ]
					},
					{ "time": 2.6667 }
				]
			},
			"left forearm": {
				"rotate": [
					{
						"curve": [ 0.317, 0, 0.95, -8.98 ]
					},
					{
						"time": 1.2667,
						"value": -8.98,
						"curve": [ 1.617, -8.98, 2.317, 0 ]
					},
					{ "time": 2.6667 }
				],
				"translate": [
					{ "curve": "stepped" },
					{ "time": 2.6667 }
				]
			},
			"left hand": {
				"rotate": [
					{
						"curve": [ 0.333, 0, 1, 14.54 ]
					},
					{
						"time": 1.3333,
						"value": 14.54,
						"curve": [ 1.667, 14.54, 2.333, 0 ]
					},
					{ "time": 2.6667 }
				],
				"translate": [
					{ "curve": "stepped" },
					{ "time": 2.6667 }
				]
			},
			"trunk": {
				"rotate": [
					{ "curve": "stepped" },
					{ "time": 2.6667 }
				],
				"translate": [
					{
						"curve": [ 0.333, 0, 1, -1.7, 0.333, 0, 1, -17.01 ]
					},
					{
						"time": 1.3333,
						"x": -1.7,
						"y": -17.01,
						"curve": [ 1.667, -1.7, 2.333, 0, 1.667, -17.01, 2.333, 0 ]
					},
					{ "time": 2.6667 }
				]
			},
			"foot": {
				"rotate": [
					{ "curve": "stepped" },
					{ "time": 2.6667 }
				],
				"translate": [
					{
						"curve": [ 0.333, 0, 1, 20.45, 0.333, 0, 1, -4.94 ]
					},
					{
						"time": 1.3333,
						"x": 20.45,
						"y": -4.94,
						"curve": [ 1.667, 20.45, 2.333, 0, 1.667, -4.94, 2.333, 0 ]
					},
					{ "time": 2.6667 }
				]
			},
			"head": {
				"rotate": [
					{
						"curve": [ 0.375, 0, 1.125, 7.32 ]
					},
					{
						"time": 1.5,
						"value": 7.32,
						"curve": [ 1.792, 7.32, 2.375, 0 ]
					},
					{ "time": 2.6667 }
				],
				"translate": [
					{
						"curve": [ 0.375, 0, 1.125, -3.37, 0.375, 0, 1.125, -2.59 ]
					},
					{
						"time": 1.5,
						"x": -3.37,
						"y": -2.59,
						"curve": [ 1.792, -3.37, 2.375, 0, 1.792, -2.59, 2.375, 0 ]
					},
					{ "time": 2.6667 }
				]
			},
			"right forearm": {
				"rotate": [
					{
						"curve": [ 0.167, 0, 0.5, 15.53 ]
					},
					{
						"time": 0.6667,
						"value": 15.53,
						"curve": [ 0.708, 15.53, 0.792, -39.48 ]
					},
					{
						"time": 0.8333,
						"value": -39.48,
						"curve": [ 0.9, -39.48, 1.033, -42.45 ]
					},
					{
						"time": 1.1,
						"value": -42.45,
						"curve": [ 1.217, -42.45, 1.45, -39.06 ]
					},
					{
						"time": 1.5667,
						"value": -39.06,
						"curve": [ 1.717, -39.06, 2.017, -42.68 ]
					},
					{
						"time": 2.1667,
						"value": -42.68,
						"curve": [ 2.208, -42.68, 2.292, 3.83 ]
					},
					{
						"time": 2.3333,
						"value": 3.83,
						"curve": [ 2.417, 3.83, 2.583, 0 ]
					},
					{ "time": 2.6667 }
				],
				"translate": [
					{ "curve": "stepped" },
					{ "time": 2.6667 }
				]
			},
			"right hand": {
				"rotate": [
					{
						"curve": [ 0.175, 0, 0.525, 13.05 ]
					},
					{
						"time": 0.7,
						"value": 13.05,
						"curve": [ 0.767, 13.05, 0.9, -19.42 ]
					},
					{
						"time": 0.9667,
						"value": -19.42,
						"curve": [ 1.175, -19.42, 1.592, -3.16 ]
					},
					{
						"time": 1.8,
						"value": -3.16,
						"curve": [ 1.883, -3.16, 2.05, -12 ]
					},
					{
						"time": 2.1333,
						"value": -12,
						"curve": [ 2.267, -12, 2.533, 0 ]
					},
					{ "time": 2.6667 }
				],
				"translate": [
					{ "curve": "stepped" },
					{ "time": 2.6667 }
				]
			},
			"right big arm": {
				"rotate": [
					{
						"curve": [ 0.325, 0, 0.975, 2.94 ]
					},
					{
						"time": 1.3,
						"value": 2.94,
						"curve": [ 1.642, 2.94, 2.325, 0 ]
					},
					{ "time": 2.6667 }
				],
				"translate": [
					{ "curve": "stepped" },
					{ "time": 2.6667 }
				]
			}
		},
		"attachments": {
			"default": {
				"dress": {
					"dress": {
						"deform": [
							{
								"curve": [ 0.333, 0, 1, 1 ]
							},
							{
								"time": 1.3333,
								"vertices": [ 1.42603, -2.85196, 3.32605, -4.98898, 1.66302, -9.97797, 6.17792, -14.25601, 6.17792, -14.25601, 5.46698, 11.64096, -4.63196, 25.84, 5.94092, 17.34894, 1.66296, -1.66303, 10.45599, -8.31494, 7.604, 13.7821, 9.26691, 13.78198, 4.98895, 11.64105, 0, 5.70397, 0, 0, 0, 0, 0, 0, 23.28595, 16.63388, 7.13, 0, 2.85199, 9.98199, 2.85199, 9.98199, 2.85199, 9.98199, 2.85199, 9.98199, 1.42596, 19.78201, 1.42596, 19.78201, 1.42596, 19.78201, -2.31604, 27.26602, 4.81396, 27.26602, -4.27795, 7.12994, -4.27795, 14.61395, -6.14899, 20.22693, -6.14899, 20.22693 ],
								"curve": [ 1.667, 0, 2.333, 1 ]
							},
							{ "time": 2.6667 }
						]
					}
				},
				"head": {
					"head": {
						"deform": [
							{
								"curve": [ 0.375, 0, 1.125, 1 ]
							},
							{
								"time": 1.5,
								"vertices": [ -0.17523, -1.44469, -3.78668, -1.0098, -3.78668, -1.0098, -3.78668, -1.0098, -3.78668, -1.0098, -3.78668, -1.0098, -5.49286, -3.00301, -0.17523, -1.44469, -0.17523, -1.44469, -8.20874, -1.21021, -6.6767, -0.66176, -11.09912, -0.86217, -7.39911, -0.57477, -6.6767, -0.66176 ],
								"curve": [ 1.792, 0, 2.375, 1 ]
							},
							{ "time": 2.6667 }
						]
					}
				}
			}
		}
	}
}
}